{
    "Instance": "Corners486_G23",
    "Objective": 259,
    "Infeasibility": 0.0,
    "Starting Time": 1711828461.262914,
    "Time Taken": 39.79557657241821,
    "Initialization Time": 5.585662364959717,
    "nrInitSolutions": 100,
    "startingLambda": 0.1,
    "nrDistricts": 10,
    "lambdaRange": [
        0.1,
        0.4,
        0.7,
        1
    ],
    "delta": 0.05,
    "llambda": 0.7,
    "rcl_parameter": 0.3,
    "Allocation": {
        "0": [
            "676",
            "677",
            "675",
            "703",
            "648",
            "702",
            "651",
            "650",
            "623",
            "705",
            "622",
            "706",
            "627",
            "654",
            "515",
            "542",
            "488",
            "680",
            "487",
            "541",
            "356",
            "379",
            "380",
            "328",
            "378",
            "433",
            "486",
            "352",
            "513",
            "461",
            "383",
            "568",
            "384",
            "567",
            "594",
            "385",
            "460",
            "351",
            "405",
            "355",
            "686",
            "685",
            "713",
            "632",
            "682",
            "578",
            "663",
            "660",
            "652",
            "600"
        ],
        "1": [
            "267",
            "239",
            "240",
            "238",
            "211",
            "212",
            "185",
            "159",
            "186",
            "160",
            "161",
            "134",
            "133",
            "188",
            "106",
            "215",
            "79",
            "214",
            "80",
            "52",
            "51",
            "78",
            "25",
            "24",
            "26",
            "50",
            "74",
            "101",
            "102",
            "103",
            "130",
            "48",
            "76",
            "104",
            "131",
            "49",
            "73",
            "46",
            "125",
            "151",
            "98",
            "19",
            "124",
            "206",
            "180",
            "149",
            "175",
            "205",
            "233"
        ],
        "2": [
            "391",
            "418",
            "417",
            "445",
            "444",
            "416",
            "446",
            "472",
            "473",
            "527",
            "555",
            "502",
            "529",
            "556",
            "530",
            "557",
            "583",
            "531",
            "532",
            "558",
            "533",
            "505",
            "534",
            "506",
            "507",
            "535",
            "478",
            "480",
            "508",
            "453",
            "481",
            "476",
            "509",
            "449",
            "454",
            "448",
            "510",
            "421",
            "483",
            "429",
            "616",
            "427",
            "590",
            "670",
            "614",
            "401",
            "455",
            "613",
            "261",
            "126",
            "283"
        ],
        "3": [
            "81",
            "27",
            "54",
            "28",
            "56",
            "0",
            "29",
            "57",
            "58",
            "31",
            "112",
            "85",
            "32",
            "111",
            "110",
            "113",
            "5",
            "138",
            "6",
            "60",
            "114",
            "7",
            "140",
            "8",
            "61",
            "137",
            "136",
            "135",
            "164",
            "109",
            "163",
            "141",
            "168",
            "195",
            "190",
            "194",
            "221",
            "217",
            "193",
            "216",
            "166",
            "243",
            "270",
            "297",
            "247",
            "326",
            "218",
            "275"
        ],
        "4": [
            "296",
            "323",
            "322",
            "349",
            "321",
            "348",
            "376",
            "320",
            "375",
            "403",
            "402",
            "319",
            "293",
            "404",
            "374",
            "430",
            "318",
            "345",
            "346",
            "400",
            "428",
            "344",
            "399",
            "343",
            "371",
            "342",
            "398",
            "236",
            "370",
            "368",
            "288",
            "395",
            "367",
            "397",
            "457",
            "340",
            "339",
            "458",
            "593",
            "477",
            "554",
            "501",
            "639",
            "643",
            "423",
            "230",
            "392"
        ],
        "5": [
            "330",
            "254",
            "253",
            "281",
            "226",
            "308",
            "273",
            "300",
            "246",
            "272",
            "245",
            "307",
            "309",
            "335",
            "219",
            "362",
            "299",
            "192",
            "361",
            "337",
            "333",
            "413",
            "387",
            "441",
            "414",
            "440",
            "271",
            "63",
            "439",
            "466",
            "465",
            "492",
            "464",
            "463",
            "437",
            "517",
            "490",
            "409",
            "436",
            "516",
            "544",
            "408",
            "571",
            "381",
            "354",
            "572",
            "570",
            "598"
        ],
        "6": [
            "547",
            "520",
            "521",
            "522",
            "495",
            "523",
            "549",
            "576",
            "524",
            "496",
            "550",
            "577",
            "497",
            "551",
            "469",
            "630",
            "498",
            "579",
            "552",
            "631",
            "605",
            "633",
            "661",
            "688",
            "687",
            "689",
            "662",
            "690",
            "714",
            "717",
            "712",
            "715",
            "636",
            "718",
            "637",
            "625",
            "709",
            "684",
            "708",
            "683",
            "599",
            "681",
            "656",
            "626",
            "649",
            "678",
            "603",
            "597"
        ],
        "7": [
            "692",
            "693",
            "665",
            "666",
            "667",
            "720",
            "612",
            "668",
            "694",
            "721",
            "695",
            "611",
            "696",
            "722",
            "697",
            "723",
            "587",
            "615",
            "724",
            "698",
            "725",
            "726",
            "589",
            "727",
            "562",
            "700",
            "728",
            "673",
            "646",
            "591",
            "618",
            "592",
            "644",
            "619",
            "566",
            "620",
            "539",
            "538",
            "537",
            "511",
            "484",
            "420",
            "500",
            "581",
            "229",
            "284",
            "285",
            "260"
        ],
        "8": [
            "97",
            "178",
            "150",
            "179",
            "232",
            "181",
            "207",
            "231",
            "182",
            "234",
            "183",
            "155",
            "235",
            "156",
            "336",
            "311",
            "316",
            "396",
            "317",
            "262",
            "115",
            "282",
            "9",
            "86",
            "313",
            "314",
            "315",
            "304",
            "360",
            "170",
            "120",
            "366",
            "289",
            "303",
            "15",
            "228",
            "451",
            "41",
            "99",
            "278",
            "44",
            "69",
            "305",
            "72",
            "274",
            "251",
            "252",
            "250",
            "100"
        ],
        "9": [
            "43",
            "17",
            "16",
            "42",
            "14",
            "13",
            "12",
            "40",
            "39",
            "38",
            "93",
            "66",
            "65",
            "92",
            "64",
            "147",
            "91",
            "148",
            "90",
            "117",
            "146",
            "116",
            "62",
            "36",
            "89",
            "35",
            "173",
            "200",
            "172",
            "171",
            "198",
            "197",
            "255",
            "388",
            "87",
            "369",
            "363",
            "10",
            "263",
            "334",
            "88",
            "331",
            "264",
            "372",
            "201",
            "302",
            "450",
            "257"
        ]
    },
    "Infeasibility Breakdown": {
        "Customers Infeasibility": {
            "0": 0.0,
            "1": 0.0,
            "2": 0.0,
            "3": 0.0,
            "4": 0.0,
            "5": 0.0,
            "6": 0.0,
            "7": 0.0,
            "8": 0.0,
            "9": 0.0
        },
        "Demand Infeasibility": {
            "0": 0.0,
            "1": 0.0,
            "2": 0.0,
            "3": 0.0,
            "4": 0.0,
            "5": 0.0,
            "6": 0.0,
            "7": 0.0,
            "8": 0.0,
            "9": 0.0
        },
        "Workload Infeasibility": {
            "0": 0.0,
            "1": 0.0,
            "2": 0.0,
            "3": 0.0,
            "4": 0.0,
            "5": 0.0,
            "6": 0.0,
            "7": 0.0,
            "8": 0.0,
            "9": 0.0
        }
    },
    "Objective Analysis": [
        185,
        183,
        189,
        200,
        200,
        200,
        200,
        209,
        209,
        209,
        219,
        236,
        236,
        259,
        259
    ],
    "Infeasibility Analysis": [
        4.492343961306065,
        1.5673315785413453,
        1.4468811867350821,
        1.0435621518400093,
        1.0354583988823325,
        1.0303339369735407,
        1.0303339369735405,
        0.8660989937453406,
        0.8660417035706054,
        0.8572749742058707,
        0.670693484124712,
        0.36466690571514637,
        0.3250329651757005,
        0.0011171584073327776,
        0.0
    ],
    "solutions_collection": [
        {
            "objective": 185,
            "infeasibility": 4.492343961306065,
            "merit": 0.7495590714552818,
            "lambda": 0.1,
            "time": 1711828466.8499773
        },
        {
            "objective": 183,
            "infeasibility": 1.5673315785413453,
            "merit": 0.4538110799320566,
            "lambda": 0.1,
            "iLambda": 0,
            "time": 1711828468.5875993
        },
        {
            "objective": 189,
            "infeasibility": 1.4468811867350821,
            "merit": 0.45150630049169005,
            "lambda": 0.1,
            "iLambda": 0,
            "time": 1711828469.2073903
        },
        {
            "objective": 200,
            "infeasibility": 1.0435621518400093,
            "merit": 0.42903153985932563,
            "lambda": 0.1,
            "iLambda": 0,
            "time": 1711828470.2472987
        },
        {
            "objective": 200,
            "infeasibility": 1.0354583988823325,
            "merit": 0.4282211645635579,
            "lambda": 0.1,
            "iLambda": 0,
            "time": 1711828470.7739246
        },
        {
            "objective": 200,
            "infeasibility": 1.0303339369735407,
            "merit": 0.42770871837267876,
            "lambda": 0.1,
            "iLambda": 0,
            "time": 1711828471.4087262
        },
        {
            "objective": 200,
            "infeasibility": 1.0303339369735405,
            "merit": 0.4277087183726787,
            "lambda": 0.1,
            "iLambda": 0,
            "time": 1711828471.617888
        },
        {
            "objective": 209,
            "infeasibility": 0.8660989937453406,
            "merit": 0.42589561366024836,
            "lambda": 0.1,
            "iLambda": 0,
            "time": 1711828472.0444636
        },
        {
            "objective": 209,
            "infeasibility": 0.8660417035706054,
            "merit": 0.42588988464277483,
            "lambda": 0.1,
            "iLambda": 0,
            "time": 1711828472.8772566
        },
        {
            "objective": 209,
            "infeasibility": 0.8572749742058707,
            "merit": 0.42501321170630135,
            "lambda": 0.1,
            "iLambda": 0,
            "time": 1711828473.500984
        },
        {
            "objective": 219,
            "infeasibility": 0.670693484124712,
            "merit": 0.4225888289319517,
            "lambda": 0.1,
            "iLambda": 0,
            "time": 1711828474.1228974
        },
        {
            "objective": 236,
            "infeasibility": 0.36466690571514637,
            "merit": 0.41958357368839777,
            "lambda": 0.1,
            "iLambda": 0,
            "time": 1711828474.8547952
        },
        {
            "objective": 236,
            "infeasibility": 0.3250329651757005,
            "merit": 0.4156201796344532,
            "lambda": 0.1,
            "iLambda": 0,
            "time": 1711828475.1657078
        },
        {
            "objective": 259,
            "infeasibility": 0.0011171584073327776,
            "merit": 0.42090140881747856,
            "lambda": 0.4,
            "iLambda": 1,
            "time": 1711828479.7164094
        },
        {
            "objective": 259,
            "infeasibility": 0.0,
            "merit": 0.42045454545454547,
            "lambda": 0.4,
            "iLambda": 1,
            "time": 1711828480.8640165
        }
    ]
}