{
    "Instance": "Diagonal486_G20",
    "Objective": 236,
    "Infeasibility": 0.0,
    "Starting Time": 1711828501.0622933,
    "Time Taken": 45.98301362991333,
    "Initialization Time": 5.608670711517334,
    "nrInitSolutions": 100,
    "startingLambda": 0.1,
    "nrDistricts": 10,
    "lambdaRange": [
        0.1,
        0.4,
        0.7,
        1
    ],
    "delta": 0.05,
    "llambda": 0.7,
    "rcl_parameter": 0.3,
    "Allocation": {
        "0": [
            "0",
            "27",
            "54",
            "28",
            "30",
            "81",
            "29",
            "56",
            "31",
            "3",
            "32",
            "4",
            "83",
            "33",
            "110",
            "84",
            "34",
            "6",
            "109",
            "136",
            "137",
            "35",
            "135",
            "36",
            "37",
            "39",
            "91",
            "10",
            "90",
            "65",
            "92",
            "89",
            "12",
            "13",
            "42",
            "41",
            "43",
            "44",
            "18",
            "14",
            "199",
            "19",
            "11",
            "148",
            "75",
            "63"
        ],
        "1": [
            "624",
            "568",
            "626",
            "680",
            "570",
            "541",
            "599",
            "540",
            "514",
            "567",
            "543",
            "516",
            "488",
            "461",
            "707",
            "544",
            "487",
            "572",
            "545",
            "462",
            "460",
            "627",
            "681",
            "708",
            "486",
            "571",
            "629",
            "684",
            "459",
            "711",
            "710",
            "628",
            "513",
            "630",
            "602",
            "432",
            "603",
            "656",
            "682",
            "655",
            "638",
            "448",
            "476",
            "556",
            "379",
            "654",
            "551",
            "338",
            "284",
            "608"
        ],
        "2": [
            "727",
            "700",
            "701",
            "673",
            "646",
            "672",
            "671",
            "698",
            "697",
            "670",
            "643",
            "642",
            "724",
            "723",
            "615",
            "722",
            "614",
            "588",
            "507",
            "480",
            "508",
            "481",
            "453",
            "479",
            "452",
            "539",
            "538",
            "566",
            "537",
            "559",
            "536",
            "348",
            "563",
            "484",
            "430",
            "457",
            "320",
            "564",
            "485",
            "349",
            "618",
            "373",
            "562",
            "323",
            "403",
            "590",
            "321"
        ],
        "3": [
            "216",
            "217",
            "218",
            "245",
            "244",
            "219",
            "192",
            "165",
            "193",
            "166",
            "194",
            "139",
            "195",
            "222",
            "112",
            "221",
            "140",
            "168",
            "248",
            "141",
            "169",
            "247",
            "249",
            "114",
            "250",
            "274",
            "251",
            "301",
            "225",
            "226",
            "227",
            "254",
            "172",
            "200",
            "201",
            "144",
            "145",
            "202",
            "230",
            "204",
            "143",
            "176",
            "149",
            "170",
            "177",
            "197",
            "205",
            "38",
            "180",
            "208"
        ],
        "4": [
            "285",
            "311",
            "282",
            "387",
            "415",
            "279",
            "414",
            "386",
            "416",
            "413",
            "359",
            "417",
            "443",
            "385",
            "444",
            "440",
            "358",
            "412",
            "384",
            "445",
            "471",
            "467",
            "357",
            "411",
            "409",
            "491",
            "497",
            "521",
            "499",
            "501",
            "356",
            "463",
            "436",
            "410",
            "494",
            "522",
            "354",
            "523",
            "520",
            "355",
            "465",
            "500",
            "329",
            "498",
            "550",
            "578",
            "290",
            "306",
            "347",
            "280"
        ],
        "5": [
            "528",
            "584",
            "611",
            "526",
            "582",
            "612",
            "554",
            "665",
            "666",
            "664",
            "637",
            "636",
            "635",
            "553",
            "609",
            "634",
            "580",
            "661",
            "718",
            "719",
            "687",
            "606",
            "688",
            "716",
            "631",
            "658",
            "690",
            "632",
            "660",
            "691",
            "552",
            "662",
            "692",
            "667",
            "633",
            "607",
            "717",
            "663",
            "686",
            "604",
            "659",
            "569",
            "648",
            "651",
            "622",
            "678",
            "679",
            "583",
            "496"
        ],
        "6": [
            "48",
            "49",
            "71",
            "73",
            "102",
            "50",
            "77",
            "129",
            "103",
            "78",
            "80",
            "105",
            "23",
            "106",
            "53",
            "52",
            "159",
            "107",
            "134",
            "161",
            "104",
            "160",
            "158",
            "188",
            "24",
            "215",
            "185",
            "310",
            "337",
            "335",
            "309",
            "314",
            "369",
            "119",
            "203",
            "336",
            "345",
            "342",
            "388",
            "184",
            "368",
            "307",
            "339",
            "241",
            "361",
            "151",
            "315"
        ],
        "7": [
            "382",
            "381",
            "327",
            "380",
            "438",
            "437",
            "407",
            "406",
            "434",
            "464",
            "378",
            "518",
            "519",
            "546",
            "573",
            "495",
            "547",
            "490",
            "574",
            "325",
            "298",
            "324",
            "351",
            "575",
            "548",
            "549",
            "596",
            "652",
            "625",
            "577",
            "653",
            "650",
            "502",
            "675",
            "702",
            "676",
            "621",
            "704",
            "649",
            "449",
            "703",
            "515",
            "503",
            "474",
            "530",
            "557",
            "709",
            "623",
            "527"
        ],
        "8": [
            "150",
            "178",
            "179",
            "152",
            "206",
            "123",
            "122",
            "232",
            "124",
            "147",
            "233",
            "96",
            "120",
            "94",
            "67",
            "68",
            "128",
            "235",
            "262",
            "99",
            "127",
            "98",
            "236",
            "126",
            "153",
            "72",
            "207",
            "261",
            "263",
            "209",
            "237",
            "155",
            "64",
            "101",
            "70",
            "130",
            "45",
            "121",
            "20",
            "79",
            "17",
            "362",
            "334",
            "287",
            "157",
            "26",
            "238"
        ],
        "9": [
            "404",
            "617",
            "561",
            "376",
            "350",
            "322",
            "296",
            "589",
            "266",
            "343",
            "212",
            "344",
            "428",
            "399",
            "374",
            "239",
            "265",
            "370",
            "372",
            "316",
            "318",
            "346",
            "401",
            "268",
            "319",
            "267",
            "317",
            "560",
            "587",
            "291",
            "240",
            "398",
            "365",
            "366",
            "213",
            "242",
            "313",
            "367",
            "183",
            "187",
            "293",
            "511",
            "132",
            "51",
            "211",
            "186",
            "131",
            "74",
            "47",
            "288",
            "534"
        ]
    },
    "Infeasibility Breakdown": {
        "Customers Infeasibility": {
            "0": 0.0,
            "1": 0.0,
            "2": 0.0,
            "3": 0.0,
            "4": 0.0,
            "5": 0.0,
            "6": 0.0,
            "7": 0.0,
            "8": 0.0,
            "9": 0.0
        },
        "Demand Infeasibility": {
            "0": 0.0,
            "1": 0.0,
            "2": 0.0,
            "3": 0.0,
            "4": 0.0,
            "5": 0.0,
            "6": 0.0,
            "7": 0.0,
            "8": 0.0,
            "9": 0.0
        },
        "Workload Infeasibility": {
            "0": 0.0,
            "1": 0.0,
            "2": 0.0,
            "3": 0.0,
            "4": 0.0,
            "5": 0.0,
            "6": 0.0,
            "7": 0.0,
            "8": 0.0,
            "9": 0.0
        }
    },
    "Objective Analysis": [
        169,
        180,
        180,
        224,
        224,
        252,
        252,
        252,
        251,
        244,
        242,
        237,
        236
    ],
    "Infeasibility Analysis": [
        8.499539608881772,
        4.305973377704662,
        4.29354414456004,
        1.485008040922267,
        1.463324077812492,
        0.010642424681869109,
        0.004919696914766236,
        0.0,
        0.0,
        0.0,
        0.0,
        0.0,
        0.0
    ],
    "solutions_collection": [
        {
            "objective": 169,
            "infeasibility": 8.499539608881772,
            "merit": 1.1617620789693581,
            "lambda": 0.1,
            "time": 1711828506.6724515
        },
        {
            "objective": 180,
            "infeasibility": 4.305973377704662,
            "merit": 0.7627006588036765,
            "lambda": 0.1,
            "iLambda": 0,
            "time": 1711828509.0314329
        },
        {
            "objective": 180,
            "infeasibility": 4.29354414456004,
            "merit": 0.7614577354892144,
            "lambda": 0.1,
            "iLambda": 0,
            "time": 1711828509.3457294
        },
        {
            "objective": 224,
            "infeasibility": 1.485008040922267,
            "merit": 0.5617849369335551,
            "lambda": 0.1,
            "iLambda": 0,
            "time": 1711828512.6529458
        },
        {
            "objective": 224,
            "infeasibility": 1.463324077812492,
            "merit": 0.5596165406225776,
            "lambda": 0.1,
            "iLambda": 0,
            "time": 1711828513.169721
        },
        {
            "objective": 252,
            "infeasibility": 0.010642424681869109,
            "merit": 0.46600889191468137,
            "lambda": 0.1,
            "iLambda": 0,
            "time": 1711828516.6721787
        },
        {
            "objective": 252,
            "infeasibility": 0.004919696914766236,
            "merit": 0.4654366191379711,
            "lambda": 0.1,
            "iLambda": 0,
            "time": 1711828516.8798642
        },
        {
            "objective": 252,
            "infeasibility": 0.0,
            "merit": 0.46494464944649444,
            "lambda": 0.1,
            "iLambda": 0,
            "time": 1711828517.0890799
        },
        {
            "objective": 251,
            "infeasibility": 0.0,
            "merit": 0.46309963099630996,
            "lambda": 0.1,
            "iLambda": 0,
            "time": 1711828518.1239161
        },
        {
            "objective": 244,
            "infeasibility": 0.0,
            "merit": 0.45018450184501846,
            "lambda": 0.7,
            "iLambda": 2,
            "time": 1711828523.6644385
        },
        {
            "objective": 242,
            "infeasibility": 0.0,
            "merit": 0.44649446494464945,
            "lambda": 0.7,
            "iLambda": 2,
            "time": 1711828523.979619
        },
        {
            "objective": 237,
            "infeasibility": 0.0,
            "merit": 0.43726937269372695,
            "lambda": 0.7,
            "iLambda": 2,
            "time": 1711828525.4369202
        },
        {
            "objective": 236,
            "infeasibility": 0.0,
            "merit": 0.4354243542435424,
            "lambda": 0.7,
            "iLambda": 2,
            "time": 1711828526.4784248
        }
    ]
}