{
    "Instance": "Center726_G16",
    "Objective": 227,
    "Infeasibility": 0.0,
    "Starting Time": 1711828725.7190864,
    "Time Taken": 129.98785710334778,
    "Initialization Time": 10.901097297668457,
    "nrInitSolutions": 100,
    "startingLambda": 0.1,
    "nrDistricts": 10,
    "lambdaRange": [
        0.1,
        0.4,
        0.7,
        1
    ],
    "delta": 0.05,
    "llambda": 0.7,
    "rcl_parameter": 0.3,
    "Allocation": {
        "0": [
            "497",
            "496",
            "466",
            "464",
            "467",
            "663",
            "463",
            "629",
            "465",
            "468",
            "495",
            "434",
            "433",
            "430",
            "432",
            "528",
            "696",
            "561",
            "400",
            "399",
            "628",
            "401",
            "562",
            "435",
            "402",
            "695",
            "367",
            "471",
            "366",
            "661",
            "403",
            "472",
            "333",
            "365",
            "364",
            "693",
            "300",
            "506",
            "334",
            "541",
            "439",
            "372",
            "505",
            "370",
            "540",
            "338",
            "436",
            "408",
            "332",
            "574",
            "396",
            "406",
            "371",
            "507",
            "438",
            "728",
            "441",
            "440",
            "369",
            "575",
            "404",
            "469",
            "232",
            "204",
            "265",
            "532",
            "68",
            "71",
            "176",
            "175",
            "209",
            "636",
            "172",
            "36"
        ],
        "1": [
            "20",
            "21",
            "22",
            "23",
            "24",
            "57",
            "25",
            "89",
            "58",
            "90",
            "26",
            "88",
            "59",
            "91",
            "27",
            "123",
            "92",
            "93",
            "155",
            "154",
            "188",
            "187",
            "158",
            "94",
            "189",
            "191",
            "222",
            "126",
            "159",
            "220",
            "127",
            "192",
            "224",
            "254",
            "257",
            "258",
            "290",
            "255",
            "128",
            "95",
            "193",
            "226",
            "162",
            "286",
            "227",
            "160",
            "130",
            "161",
            "289",
            "62",
            "260",
            "63",
            "29",
            "293",
            "294",
            "96",
            "288",
            "30",
            "351",
            "322",
            "31",
            "32",
            "98",
            "225",
            "65",
            "64",
            "326",
            "392",
            "362",
            "718"
        ],
        "2": [
            "923",
            "956",
            "955",
            "954",
            "1020",
            "953",
            "921",
            "952",
            "986",
            "1054",
            "985",
            "888",
            "1055",
            "1018",
            "1086",
            "984",
            "1017",
            "1051",
            "983",
            "1050",
            "1052",
            "1085",
            "1084",
            "853",
            "1083",
            "820",
            "1082",
            "821",
            "854",
            "819",
            "786",
            "822",
            "823",
            "755",
            "790",
            "824",
            "856",
            "791",
            "852",
            "753",
            "722",
            "754",
            "723",
            "758",
            "725",
            "809",
            "488",
            "659",
            "616",
            "624",
            "780",
            "559",
            "626",
            "525",
            "691",
            "487",
            "560",
            "757",
            "625",
            "622",
            "587",
            "977",
            "483",
            "644",
            "645",
            "646",
            "423",
            "1087",
            "883",
            "717",
            "545",
            "1013",
            "552"
        ],
        "3": [
            "78",
            "79",
            "80",
            "81",
            "114",
            "115",
            "116",
            "149",
            "182",
            "117",
            "118",
            "83",
            "215",
            "151",
            "50",
            "214",
            "17",
            "213",
            "246",
            "16",
            "279",
            "280",
            "278",
            "311",
            "277",
            "276",
            "244",
            "313",
            "346",
            "344",
            "211",
            "347",
            "379",
            "343",
            "145",
            "178",
            "412",
            "445",
            "413",
            "146",
            "478",
            "414",
            "381",
            "447",
            "206",
            "139",
            "140",
            "141",
            "173",
            "205",
            "241",
            "274",
            "109",
            "207",
            "174",
            "107",
            "142",
            "240",
            "171",
            "273",
            "208",
            "239",
            "138",
            "106",
            "238",
            "170",
            "74",
            "73",
            "177",
            "237",
            "10",
            "41"
        ],
        "4": [
            "1069",
            "1036",
            "772",
            "740",
            "706",
            "739",
            "673",
            "674",
            "705",
            "675",
            "704",
            "703",
            "708",
            "702",
            "736",
            "709",
            "669",
            "735",
            "769",
            "734",
            "768",
            "637",
            "635",
            "603",
            "802",
            "767",
            "634",
            "602",
            "638",
            "800",
            "835",
            "733",
            "801",
            "766",
            "833",
            "601",
            "834",
            "700",
            "732",
            "569",
            "868",
            "765",
            "867",
            "731",
            "798",
            "699",
            "866",
            "698",
            "832",
            "797",
            "900",
            "537",
            "632",
            "503",
            "630",
            "566",
            "536",
            "730",
            "567",
            "568",
            "697",
            "570",
            "600",
            "535",
            "899",
            "664",
            "763",
            "500",
            "660",
            "929",
            "596",
            "794",
            "930"
        ],
        "5": [
            "578",
            "611",
            "684",
            "650",
            "749",
            "651",
            "685",
            "781",
            "782",
            "652",
            "750",
            "783",
            "687",
            "618",
            "719",
            "619",
            "817",
            "688",
            "655",
            "586",
            "654",
            "554",
            "620",
            "720",
            "521",
            "553",
            "520",
            "689",
            "690",
            "519",
            "752",
            "555",
            "584",
            "556",
            "656",
            "623",
            "486",
            "779",
            "485",
            "452",
            "589",
            "518",
            "484",
            "453",
            "588",
            "451",
            "590",
            "810",
            "551",
            "482",
            "515",
            "514",
            "550",
            "517",
            "321",
            "386",
            "352",
            "493",
            "319",
            "353",
            "320",
            "526",
            "920",
            "686",
            "716",
            "919",
            "847",
            "816",
            "848",
            "850",
            "880",
            "881",
            "585",
            "788",
            "592",
            "679",
            "422",
            "1011"
        ],
        "6": [
            "494",
            "461",
            "460",
            "428",
            "395",
            "427",
            "426",
            "393",
            "361",
            "360",
            "329",
            "328",
            "524",
            "593",
            "491",
            "295",
            "391",
            "296",
            "591",
            "424",
            "390",
            "458",
            "262",
            "358",
            "490",
            "658",
            "357",
            "229",
            "230",
            "324",
            "692",
            "291",
            "197",
            "389",
            "724",
            "489",
            "228",
            "756",
            "522",
            "196",
            "163",
            "292",
            "263",
            "455",
            "261",
            "657",
            "164",
            "421",
            "259",
            "325",
            "420",
            "419",
            "387",
            "356",
            "418",
            "354",
            "355",
            "195",
            "157",
            "223",
            "129",
            "256",
            "190",
            "124",
            "253",
            "122",
            "56",
            "721",
            "683"
        ],
        "7": [
            "1056",
            "990",
            "1023",
            "1024",
            "991",
            "957",
            "1025",
            "992",
            "959",
            "924",
            "925",
            "891",
            "1026",
            "858",
            "1058",
            "1059",
            "1027",
            "1060",
            "825",
            "859",
            "994",
            "1028",
            "860",
            "995",
            "1029",
            "893",
            "1062",
            "962",
            "1030",
            "1031",
            "963",
            "828",
            "862",
            "895",
            "1064",
            "863",
            "1032",
            "999",
            "1033",
            "966",
            "896",
            "795",
            "762",
            "997",
            "998",
            "793",
            "965",
            "897",
            "927",
            "964",
            "933",
            "898",
            "830",
            "934",
            "865",
            "932",
            "727",
            "759",
            "726",
            "597",
            "595",
            "662",
            "694",
            "530",
            "796",
            "894",
            "861",
            "760"
        ],
        "8": [
            "43",
            "9",
            "42",
            "75",
            "7",
            "40",
            "72",
            "105",
            "70",
            "104",
            "137",
            "38",
            "37",
            "272",
            "203",
            "103",
            "236",
            "69",
            "35",
            "136",
            "2",
            "4",
            "269",
            "135",
            "134",
            "3",
            "34",
            "270",
            "268",
            "167",
            "101",
            "166",
            "200",
            "303",
            "304",
            "201",
            "233",
            "267",
            "100",
            "165",
            "266",
            "168",
            "231",
            "299",
            "1",
            "302",
            "306",
            "99",
            "298",
            "307",
            "33",
            "132",
            "0",
            "199",
            "264",
            "234",
            "66",
            "102",
            "198",
            "297",
            "330",
            "331",
            "67",
            "398",
            "429",
            "397",
            "470",
            "502",
            "499",
            "531",
            "534",
            "564",
            "598",
            "631",
            "533",
            "565",
            "594",
            "633"
        ],
        "9": [
            "1072",
            "1073",
            "1074",
            "1041",
            "1008",
            "1042",
            "1043",
            "1010",
            "1045",
            "1012",
            "976",
            "943",
            "979",
            "1046",
            "1014",
            "980",
            "946",
            "1079",
            "1047",
            "981",
            "1015",
            "1080",
            "982",
            "1016",
            "1048",
            "913",
            "948",
            "914",
            "916",
            "915",
            "882",
            "844",
            "715",
            "908",
            "907",
            "942",
            "909",
            "812",
            "987",
            "950",
            "951",
            "988",
            "875",
            "906",
            "681",
            "751",
            "890",
            "905",
            "904",
            "939",
            "937",
            "839",
            "838",
            "970",
            "814",
            "815",
            "682",
            "805",
            "1003",
            "811",
            "818",
            "748",
            "649",
            "1021",
            "918",
            "917",
            "885",
            "886",
            "884",
            "872",
            "680"
        ]
    },
    "Infeasibility Breakdown": {
        "Customers Infeasibility": {
            "0": 0.0,
            "1": 0.0,
            "2": 0.0,
            "3": 0.0,
            "4": 0.0,
            "5": 0.0,
            "6": 0.0,
            "7": 0.0,
            "8": 0.0,
            "9": 0.0
        },
        "Demand Infeasibility": {
            "0": 0.0,
            "1": 0.0,
            "2": 0.0,
            "3": 0.0,
            "4": 0.0,
            "5": 0.0,
            "6": 0.0,
            "7": 0.0,
            "8": 0.0,
            "9": 0.0
        },
        "Workload Infeasibility": {
            "0": 0.0,
            "1": 0.0,
            "2": 0.0,
            "3": 0.0,
            "4": 0.0,
            "5": 0.0,
            "6": 0.0,
            "7": 0.0,
            "8": 0.0,
            "9": 0.0
        }
    },
    "Objective Analysis": [
        197,
        201,
        201,
        214,
        224,
        235,
        240,
        230,
        229,
        229,
        227
    ],
    "Infeasibility Analysis": [
        5.222990322081548,
        0.20250142478380445,
        0.20248036276234588,
        0.12318804668335087,
        0.06322323264861093,
        0.03103179126297784,
        0.0,
        0.0,
        0.0012178804172756916,
        0.0,
        0.0
    ],
    "solutions_collection": [
        {
            "objective": 197,
            "infeasibility": 5.222990322081548,
            "merit": 0.7489963854877866,
            "lambda": 0.1,
            "time": 1711828736.62272
        },
        {
            "objective": 201,
            "infeasibility": 0.20250142478380445,
            "merit": 0.2515504877027763,
            "lambda": 0.1,
            "iLambda": 0,
            "time": 1711828741.9782634
        },
        {
            "objective": 201,
            "infeasibility": 0.20248036276234588,
            "merit": 0.2515483815006304,
            "lambda": 0.1,
            "iLambda": 0,
            "time": 1711828748.9002564
        },
        {
            "objective": 214,
            "infeasibility": 0.12318804668335087,
            "merit": 0.2955352877182195,
            "lambda": 0.4,
            "iLambda": 1,
            "time": 1711828756.7798784
        },
        {
            "objective": 224,
            "infeasibility": 0.06322323264861093,
            "merit": 0.2830568419662338,
            "lambda": 0.4,
            "iLambda": 1,
            "time": 1711828757.499397
        },
        {
            "objective": 235,
            "infeasibility": 0.03103179126297784,
            "merit": 0.2828384932600818,
            "lambda": 0.4,
            "iLambda": 1,
            "time": 1711828760.02902
        },
        {
            "objective": 240,
            "infeasibility": 0.0,
            "merit": 0.2761795166858458,
            "lambda": 0.4,
            "iLambda": 1,
            "time": 1711828764.0990522
        },
        {
            "objective": 230,
            "infeasibility": 0.0,
            "merit": 0.2646720368239356,
            "lambda": 0.1,
            "iLambda": 0,
            "time": 1711828769.0286374
        },
        {
            "objective": 229,
            "infeasibility": 0.0012178804172756916,
            "merit": 0.26364307687947214,
            "lambda": 0.1,
            "iLambda": 0,
            "time": 1711828772.947842
        },
        {
            "objective": 229,
            "infeasibility": 0.0,
            "merit": 0.26352128883774456,
            "lambda": 0.1,
            "iLambda": 0,
            "time": 1711828773.3110056
        },
        {
            "objective": 227,
            "infeasibility": 0.0,
            "merit": 0.2612197928653625,
            "lambda": 0.4,
            "iLambda": 1,
            "time": 1711828808.6921003
        }
    ]
}