{
    "Instance": "Diagonal600_G6",
    "Objective": 257,
    "Infeasibility": 0.0,
    "Starting Time": 1692558012.9037528,
    "Time Taken": 181.8732340335846,
    "Initialization Time": 146.06758975982666,
    "nrEliteSolutions": 20,
    "i_max": 500,
    "nrDistricts": 10,
    "delta": 0.05,
    "llambda": 0.7,
    "rcl_parameter": 0.3,
    "Allocation": {
        "0": [
            "3",
            "1",
            "2",
            "0",
            "91",
            "61",
            "31",
            "60",
            "62",
            "121",
            "90",
            "120",
            "63",
            "151",
            "93",
            "152",
            "182",
            "123",
            "94",
            "212",
            "65",
            "95",
            "211",
            "125",
            "155",
            "35",
            "210",
            "241",
            "185",
            "5",
            "36",
            "156",
            "215",
            "271",
            "157",
            "301",
            "158",
            "187",
            "302",
            "128",
            "159",
            "220",
            "251",
            "194",
            "250",
            "133",
            "221",
            "71",
            "219",
            "164",
            "282",
            "132",
            "281",
            "98",
            "311",
            "222",
            "193",
            "163"
        ],
        "1": [
            "893",
            "895",
            "894",
            "896",
            "866",
            "867",
            "836",
            "868",
            "869",
            "806",
            "839",
            "898",
            "776",
            "746",
            "716",
            "777",
            "778",
            "717",
            "686",
            "687",
            "808",
            "779",
            "685",
            "657",
            "658",
            "684",
            "655",
            "659",
            "714",
            "625",
            "689",
            "595",
            "594",
            "719",
            "596",
            "593",
            "744",
            "774",
            "566",
            "564",
            "536",
            "537",
            "506",
            "505",
            "538",
            "504",
            "475",
            "568",
            "445",
            "446",
            "416",
            "444",
            "447",
            "417",
            "448",
            "477",
            "387",
            "418",
            "478",
            "449",
            "419",
            "389",
            "384",
            "265",
            "263",
            "297"
        ],
        "2": [
            "802",
            "832",
            "830",
            "831",
            "860",
            "829",
            "859",
            "889",
            "799",
            "858",
            "769",
            "857",
            "856",
            "827",
            "886",
            "855",
            "826",
            "825",
            "796",
            "854",
            "795",
            "740",
            "824",
            "853",
            "765",
            "738",
            "710",
            "823",
            "852",
            "822",
            "792",
            "762",
            "821",
            "708",
            "820",
            "737",
            "790",
            "767",
            "851",
            "819",
            "881",
            "880",
            "789",
            "760",
            "788",
            "730",
            "759",
            "729",
            "699",
            "728",
            "704",
            "664",
            "573",
            "457",
            "694",
            "613",
            "876",
            "576"
        ],
        "3": [
            "463",
            "464",
            "493",
            "494",
            "525",
            "495",
            "526",
            "527",
            "528",
            "497",
            "557",
            "498",
            "468",
            "469",
            "439",
            "470",
            "410",
            "440",
            "409",
            "408",
            "441",
            "442",
            "407",
            "382",
            "472",
            "412",
            "406",
            "352",
            "436",
            "351",
            "405",
            "353",
            "466",
            "323",
            "350",
            "324",
            "292",
            "293",
            "355",
            "356",
            "291",
            "385",
            "414",
            "290",
            "326",
            "289",
            "295",
            "357",
            "296",
            "358",
            "327",
            "237",
            "267",
            "319",
            "328",
            "236",
            "206",
            "298",
            "268"
        ],
        "4": [
            "330",
            "360",
            "361",
            "391",
            "421",
            "420",
            "451",
            "450",
            "452",
            "481",
            "482",
            "480",
            "510",
            "454",
            "483",
            "512",
            "540",
            "423",
            "424",
            "542",
            "455",
            "570",
            "513",
            "394",
            "393",
            "485",
            "600",
            "543",
            "425",
            "572",
            "602",
            "632",
            "662",
            "603",
            "692",
            "693",
            "601",
            "514",
            "630",
            "660",
            "663",
            "515",
            "574",
            "575",
            "604",
            "690",
            "516",
            "488",
            "517",
            "428",
            "426",
            "545",
            "577",
            "397",
            "396",
            "761",
            "783"
        ],
        "5": [
            "247",
            "246",
            "276",
            "275",
            "305",
            "274",
            "304",
            "335",
            "334",
            "336",
            "333",
            "365",
            "337",
            "308",
            "338",
            "339",
            "309",
            "369",
            "340",
            "310",
            "399",
            "312",
            "342",
            "252",
            "283",
            "343",
            "253",
            "344",
            "402",
            "254",
            "284",
            "285",
            "314",
            "374",
            "431",
            "286",
            "430",
            "218",
            "316",
            "460",
            "287",
            "256",
            "288",
            "257",
            "490",
            "258",
            "259",
            "229",
            "260",
            "99",
            "458",
            "453",
            "612",
            "138",
            "232",
            "325",
            "103",
            "102",
            "224"
        ],
        "6": [
            "28",
            "29",
            "27",
            "59",
            "26",
            "89",
            "25",
            "24",
            "56",
            "88",
            "119",
            "86",
            "118",
            "117",
            "116",
            "147",
            "148",
            "145",
            "84",
            "115",
            "114",
            "177",
            "144",
            "54",
            "112",
            "143",
            "174",
            "142",
            "53",
            "111",
            "208",
            "82",
            "202",
            "233",
            "23",
            "262",
            "231",
            "234",
            "22",
            "261",
            "203",
            "230",
            "201",
            "141",
            "110",
            "171",
            "170",
            "21",
            "209",
            "51",
            "20",
            "173",
            "264",
            "50",
            "269",
            "299",
            "239",
            "329",
            "200",
            "378",
            "502",
            "226",
            "140"
        ],
        "7": [
            "562",
            "621",
            "561",
            "591",
            "651",
            "652",
            "622",
            "650",
            "649",
            "653",
            "619",
            "679",
            "589",
            "616",
            "618",
            "617",
            "615",
            "646",
            "614",
            "676",
            "645",
            "644",
            "584",
            "675",
            "674",
            "583",
            "553",
            "706",
            "643",
            "642",
            "703",
            "733",
            "702",
            "736",
            "735",
            "672",
            "734",
            "732",
            "701",
            "611",
            "581",
            "580",
            "551",
            "550",
            "731",
            "700",
            "521",
            "549",
            "548",
            "522",
            "739",
            "755",
            "456",
            "791",
            "751",
            "677",
            "639",
            "571"
        ],
        "8": [
            "870",
            "871",
            "840",
            "841",
            "810",
            "872",
            "842",
            "812",
            "811",
            "782",
            "781",
            "873",
            "813",
            "814",
            "752",
            "753",
            "780",
            "750",
            "784",
            "754",
            "844",
            "815",
            "723",
            "724",
            "785",
            "874",
            "845",
            "721",
            "816",
            "817",
            "756",
            "726",
            "875",
            "725",
            "818",
            "786",
            "848",
            "849",
            "847",
            "879",
            "878",
            "665",
            "696",
            "697",
            "666",
            "667",
            "668",
            "635",
            "877",
            "638",
            "605",
            "637",
            "608",
            "609",
            "640",
            "669",
            "695",
            "607",
            "636",
            "887",
            "401",
            "372",
            "883",
            "511"
        ],
        "9": [
            "10",
            "11",
            "41",
            "12",
            "13",
            "43",
            "101",
            "72",
            "70",
            "44",
            "73",
            "162",
            "104",
            "100",
            "69",
            "105",
            "192",
            "45",
            "130",
            "75",
            "191",
            "190",
            "223",
            "106",
            "15",
            "136",
            "160",
            "137",
            "108",
            "107",
            "77",
            "168",
            "139",
            "166",
            "196",
            "109",
            "197",
            "227",
            "228",
            "198",
            "169",
            "47",
            "48",
            "49",
            "17",
            "19",
            "167",
            "178",
            "113",
            "85",
            "172",
            "354",
            "87",
            "411",
            "489",
            "322",
            "519",
            "42"
        ]
    },
    "Infeasibility Breakdown": {
        "Customers Infeasibility": {
            "0": 0.0,
            "1": 0.0,
            "2": 0.0,
            "3": 0.0,
            "4": 0.0,
            "5": 0.0,
            "6": 0.0,
            "7": 0.0,
            "8": 0.0,
            "9": 0.0
        },
        "Demand Infeasibility": {
            "0": 0.0,
            "1": 0.0,
            "2": 0.0,
            "3": 0.0,
            "4": 0.0,
            "5": 0.0,
            "6": 0.0,
            "7": 0.0,
            "8": 0.0,
            "9": 0.0
        },
        "Workload Infeasibility": {
            "0": 0.0,
            "1": 0.0,
            "2": 0.0,
            "3": 0.0,
            "4": 0.0,
            "5": 0.0,
            "6": 0.0,
            "7": 0.0,
            "8": 0.0,
            "9": 0.0
        }
    }
}