{
    "Instance": "Diagonal726_G23",
    "Objective": 274,
    "Infeasibility": 0.0,
    "Starting Time": 1711823407.519789,
    "Time Taken": 220.1255087852478,
    "Initialization Time": 177.62217664718628,
    "nrEliteSolutions": 20,
    "i_max": 500,
    "nrDistricts": 10,
    "delta": 0.05,
    "llambda": 0.7,
    "rcl_parameter": 0.3,
    "Allocation": {
        "0": [
            "691",
            "692",
            "724",
            "658",
            "625",
            "723",
            "722",
            "721",
            "689",
            "755",
            "626",
            "754",
            "788",
            "656",
            "593",
            "753",
            "787",
            "821",
            "752",
            "751",
            "854",
            "853",
            "719",
            "784",
            "855",
            "718",
            "750",
            "886",
            "686",
            "856",
            "885",
            "919",
            "889",
            "685",
            "823",
            "857",
            "687",
            "684",
            "651",
            "884",
            "824",
            "922",
            "791",
            "923",
            "851",
            "650",
            "917",
            "950",
            "949",
            "955",
            "916",
            "954",
            "951",
            "915",
            "953",
            "914",
            "947",
            "881",
            "848",
            "815",
            "986",
            "782",
            "871",
            "902",
            "774",
            "713",
            "844",
            "842"
        ],
        "1": [
            "333",
            "332",
            "266",
            "299",
            "265",
            "232",
            "264",
            "166",
            "199",
            "200",
            "167",
            "201",
            "133",
            "202",
            "234",
            "100",
            "68",
            "101",
            "102",
            "135",
            "35",
            "103",
            "34",
            "104",
            "137",
            "33",
            "66",
            "72",
            "170",
            "38",
            "5",
            "171",
            "4",
            "40",
            "204",
            "75",
            "237",
            "42",
            "236",
            "238",
            "269",
            "43",
            "8",
            "268",
            "44",
            "11",
            "301",
            "78",
            "79",
            "46",
            "112",
            "80",
            "145",
            "81",
            "178",
            "113",
            "48",
            "211",
            "15",
            "207",
            "18",
            "174",
            "16",
            "210",
            "176",
            "117",
            "12",
            "276",
            "246"
        ],
        "2": [
            "466",
            "465",
            "432",
            "399",
            "431",
            "400",
            "430",
            "397",
            "463",
            "462",
            "396",
            "495",
            "528",
            "561",
            "594",
            "595",
            "596",
            "627",
            "660",
            "693",
            "661",
            "629",
            "563",
            "597",
            "662",
            "694",
            "630",
            "530",
            "631",
            "664",
            "531",
            "665",
            "697",
            "696",
            "698",
            "666",
            "730",
            "699",
            "729",
            "763",
            "728",
            "667",
            "634",
            "635",
            "633",
            "764",
            "600",
            "599",
            "797",
            "567",
            "566",
            "766",
            "636",
            "733",
            "796",
            "668",
            "731",
            "732",
            "767",
            "701",
            "798",
            "799",
            "669",
            "637",
            "800",
            "831",
            "830",
            "702",
            "638",
            "703",
            "306",
            "891",
            "468",
            "436",
            "834",
            "541"
        ],
        "3": [
            "578",
            "545",
            "546",
            "513",
            "547",
            "514",
            "580",
            "515",
            "516",
            "614",
            "549",
            "517",
            "518",
            "582",
            "615",
            "485",
            "648",
            "551",
            "519",
            "486",
            "451",
            "452",
            "453",
            "520",
            "487",
            "418",
            "419",
            "488",
            "454",
            "553",
            "385",
            "521",
            "421",
            "455",
            "522",
            "523",
            "456",
            "457",
            "524",
            "556",
            "555",
            "422",
            "424",
            "491",
            "391",
            "525",
            "392",
            "393",
            "394",
            "361",
            "526",
            "589",
            "427",
            "490",
            "358",
            "493",
            "590",
            "360",
            "492",
            "389",
            "494",
            "461",
            "428",
            "395",
            "527",
            "591",
            "458",
            "359",
            "327",
            "426",
            "230",
            "53",
            "88",
            "142"
        ],
        "4": [
            "1055",
            "1022",
            "1021",
            "989",
            "1020",
            "1053",
            "1086",
            "1084",
            "1085",
            "1051",
            "1018",
            "1050",
            "1017",
            "1082",
            "1081",
            "1049",
            "1079",
            "1080",
            "1078",
            "1046",
            "1013",
            "1077",
            "1014",
            "981",
            "1044",
            "1010",
            "1043",
            "1042",
            "1009",
            "1041",
            "1075",
            "977",
            "1040",
            "976",
            "1039",
            "943",
            "978",
            "1073",
            "1072",
            "1038",
            "942",
            "1071",
            "909",
            "1005",
            "1037",
            "1006",
            "941",
            "1070",
            "973",
            "974",
            "1069",
            "1068",
            "1035",
            "1067",
            "1034",
            "1066",
            "1001",
            "1065",
            "1000",
            "968",
            "969",
            "936",
            "903",
            "904",
            "870",
            "869",
            "1064",
            "935",
            "837",
            "998",
            "1063",
            "841",
            "999",
            "872",
            "938"
        ],
        "5": [
            "336",
            "369",
            "370",
            "371",
            "372",
            "339",
            "340",
            "438",
            "406",
            "341",
            "471",
            "342",
            "374",
            "470",
            "343",
            "472",
            "503",
            "275",
            "310",
            "473",
            "277",
            "344",
            "311",
            "502",
            "536",
            "242",
            "506",
            "278",
            "501",
            "537",
            "534",
            "568",
            "279",
            "533",
            "540",
            "538",
            "280",
            "247",
            "313",
            "603",
            "508",
            "245",
            "346",
            "571",
            "602",
            "542",
            "500",
            "281",
            "575",
            "244",
            "212",
            "435",
            "604",
            "543",
            "213",
            "608",
            "510",
            "475",
            "442",
            "441",
            "408",
            "511",
            "249",
            "19",
            "54",
            "116",
            "73",
            "89",
            "381",
            "251",
            "150",
            "86",
            "507",
            "17",
            "14",
            "141"
        ],
        "6": [
            "1056",
            "1023",
            "1024",
            "991",
            "1025",
            "1026",
            "992",
            "1058",
            "993",
            "959",
            "1027",
            "994",
            "926",
            "1060",
            "1028",
            "995",
            "961",
            "927",
            "893",
            "925",
            "962",
            "996",
            "892",
            "928",
            "860",
            "929",
            "924",
            "963",
            "1029",
            "827",
            "997",
            "896",
            "930",
            "828",
            "859",
            "794",
            "861",
            "795",
            "957",
            "762",
            "793",
            "897",
            "898",
            "826",
            "862",
            "864",
            "865",
            "792",
            "931",
            "832",
            "760",
            "1030",
            "899",
            "1031",
            "932",
            "1062",
            "866",
            "900",
            "965",
            "933",
            "901",
            "867",
            "801",
            "768",
            "769",
            "308",
            "940",
            "434",
            "765"
        ],
        "7": [
            "646",
            "645",
            "644",
            "612",
            "643",
            "676",
            "610",
            "709",
            "675",
            "710",
            "742",
            "775",
            "808",
            "809",
            "773",
            "807",
            "806",
            "810",
            "840",
            "777",
            "839",
            "843",
            "805",
            "876",
            "873",
            "845",
            "905",
            "906",
            "744",
            "877",
            "804",
            "812",
            "971",
            "771",
            "770",
            "846",
            "907",
            "738",
            "745",
            "908",
            "847",
            "712",
            "737",
            "970",
            "814",
            "939",
            "836",
            "835",
            "714",
            "803",
            "878",
            "747",
            "911",
            "912",
            "813",
            "746",
            "879",
            "802",
            "736",
            "739",
            "735",
            "706",
            "1003",
            "673",
            "640",
            "570",
            "539",
            "405",
            "338",
            "535",
            "478"
        ],
        "8": [
            "32",
            "98",
            "65",
            "64",
            "97",
            "131",
            "63",
            "130",
            "96",
            "62",
            "30",
            "29",
            "163",
            "129",
            "197",
            "95",
            "61",
            "128",
            "162",
            "161",
            "229",
            "262",
            "194",
            "127",
            "160",
            "159",
            "193",
            "263",
            "295",
            "261",
            "126",
            "158",
            "296",
            "226",
            "260",
            "329",
            "225",
            "93",
            "92",
            "259",
            "258",
            "91",
            "58",
            "25",
            "224",
            "191",
            "59",
            "190",
            "125",
            "26",
            "124",
            "292",
            "257",
            "123",
            "157",
            "24",
            "57",
            "56",
            "55",
            "328",
            "156",
            "122",
            "155",
            "188",
            "27",
            "21",
            "77",
            "459",
            "484",
            "120",
            "74",
            "322",
            "143",
            "581"
        ],
        "9": [
            "410",
            "412",
            "411",
            "378",
            "380",
            "413",
            "348",
            "382",
            "349",
            "315",
            "316",
            "317",
            "284",
            "318",
            "283",
            "250",
            "285",
            "351",
            "217",
            "218",
            "216",
            "286",
            "184",
            "352",
            "252",
            "253",
            "215",
            "287",
            "151",
            "220",
            "186",
            "353",
            "182",
            "149",
            "288",
            "148",
            "152",
            "289",
            "321",
            "115",
            "354",
            "387",
            "355",
            "255",
            "320",
            "214",
            "356",
            "147",
            "119",
            "357",
            "222",
            "290",
            "324",
            "146",
            "325",
            "153",
            "254",
            "326",
            "180",
            "256",
            "323",
            "87",
            "181",
            "85",
            "84",
            "7",
            "196",
            "23",
            "179",
            "144",
            "164",
            "71",
            "219",
            "273"
        ]
    },
    "Infeasibility Breakdown": {
        "Customers Infeasibility": {
            "0": 0.0,
            "1": 0.0,
            "2": 0.0,
            "3": 0.0,
            "4": 0.0,
            "5": 0.0,
            "6": 0.0,
            "7": 0.0,
            "8": 0.0,
            "9": 0.0
        },
        "Demand Infeasibility": {
            "0": 0.0,
            "1": 0.0,
            "2": 0.0,
            "3": 0.0,
            "4": 0.0,
            "5": 0.0,
            "6": 0.0,
            "7": 0.0,
            "8": 0.0,
            "9": 0.0
        },
        "Workload Infeasibility": {
            "0": 0.0,
            "1": 0.0,
            "2": 0.0,
            "3": 0.0,
            "4": 0.0,
            "5": 0.0,
            "6": 0.0,
            "7": 0.0,
            "8": 0.0,
            "9": 0.0
        }
    }
}